{
  "books": [
    {
      "id": "1",
      "title": "Nhà giả kim",
      "description": "Câu chuyện về cậu bé theo đuổi giấc mơ",
      "coverUrl": "https://static.8cache.com/cover/o/eJzLyTDW1zULTa4wdYuyiA8I1A8zytT1cDIwzfDy1HeEgoC0bH1j78QU55DEcnMzRw-TwjwPf3MXT0en7NzMdJNMt8x033Rn53z9ciNDU90MYyMjAF75GZw=/nha-gia-kim-cau-chuyen-mot-giac-mo.jpg"
    },
    {
      "id": "mrazmGpTQ",
      "title": "Không gia đình",
      "description": "Câu chuyện về tình thương giữa 2 con người lạ lẫm",
      "coverUrl": "https://cdn.glitch.com/a0fd4135-1b04-45e7-b0fd-e9aac260f6c1%2F4e598e29-e292-417e-955e-99facd76ce55.image.png?v=1589525573393"
    },
    {
      "id": "KCm1qJs80",
      "title": "Hoàng tử bé",
      "description": "Hành trình tri nhận của chính chúng ta về cuộc sống",
      "coverUrl": "http://res.cloudinary.com/coders-tokyo/image/upload/v1589526826/b9ol0fq9dnluhdedxowl.jpg"
    }
  ],
  "users": [
    {
      "id": "1",
      "name": "Linh",
      "email": "linh@gmail.com",
      "password": "$2b$10$YbB8F6vwf729QwHOGew.cuTrK/KLCAybXhGHp9NvuYnaeeMT.R21a",
      "avatarUrl": "http://res.cloudinary.com/coders-tokyo/image/upload/v1589523269/nzznawsqjlwlc1ey46ea.jpg",
      "isAdmin": true,
      "wrongLoginCount": 0
    },
    {
      "id": "2",
      "name": "Yen",
      "email": "yen@gmail.com",
      "password": "$2b$10$YbB8F6vwf729QwHOGew.cuTrK/KLCAybXhGHp9NvuYnaeeMT.R21a",
      "avatarUrl": "https://stafforgserv.com.au/wp-content/uploads/2018/09/user-img.png",
      "wrongLoginCount": 0
    }
  ],
  "transactions": [
    {
      "id": "1",
      "userId": "1",
      "bookId": "1",
      "isComplete": false,
      "isAdmin": true
    },
    {
      "id": "2",
      "userId": "2",
      "bookId": "mrazmGpTQ",
      "isComplete": false
    }
  ],
  "sessions": [
    {
      "id": "kGiZKkvDqS",
      "cart": [
        null,
        2
      ]
    },
    {
      "id": "TDtKS7NVe"
    },
    {
      "id": "fz38etc8R"
    },
    {
      "id": "HtvBVscbu"
    },
    {
      "id": "fDBjMleus"
    },
    {
      "id": "OZYmadyCsr"
    },
    {
      "id": "lPmbjtCPmR"
    },
    {
      "id": "XqLlUB5WL5"
    },
    {
      "id": "Xzm5wiZCFt"
    },
    {
      "id": "CMAosxv2hb"
    },
    {
      "id": "dfGFdGsVX"
    },
    {
      "id": "adWmVzrkj"
    },
    {
      "id": "Uzw93IJrH"
    },
    {
      "id": "G-NrCG0ne"
    },
    {
      "id": "i2FMpEG76"
    },
    {
      "id": "rJSIZAnsa"
    },
    {
      "id": "CtKMYIHowR"
    },
    {
      "id": "ZsmsWpu7K"
    },
    {
      "id": "NZXAio06Ub"
    },
    {
      "id": "3qJUY3Gb6"
    },
    {
      "id": "hupYIzx5oD"
    },
    {
      "id": "kc61hylu5"
    },
    {
      "id": "wHOMvwLh4p"
    },
    {
      "id": "oesNTqbnV"
    },
    {
      "id": "8XRiOnTyMB"
    },
    {
      "id": "WNOSgP-yh9"
    },
    {
      "id": "AEVT7AZRa"
    },
    {
      "id": "122yuA1S1"
    },
    {
      "id": "yPaIpJIHv"
    },
    {
      "id": "PBJBtr1B4s"
    },
    {
      "id": "RVAe40l53v"
    },
    {
      "id": "qWw8WTKziV"
    },
    {
      "id": "spK7vGkGF"
    },
    {
      "id": "vOOtu9gjM"
    },
    {
      "id": "TiJwJhs_s"
    },
    {
      "id": "r8ogFGSCp"
    },
    {
      "id": "hHDCHdXf0"
    },
    {
      "id": "7kkr55i6pl"
    },
    {
      "id": "gVrycMOmX"
    },
    {
      "id": "MJSQXNoHM"
    },
    {
      "id": "V8T1x3W1W"
    },
    {
      "id": "zkYs7Ug5L"
    },
    {
      "id": "z8Ta7pyzB"
    },
    {
      "id": "D_Qs5Vugl"
    },
    {
      "id": "tuhsQC2Nt"
    },
    {
      "id": "kf_fSP00V"
    },
    {
      "id": "5PGzWc3W6"
    },
    {
      "id": "9E1atrFbtQ"
    },
    {
      "id": "2VvD9vmRZ"
    },
    {
      "id": "Bg93-ia0t"
    },
    {
      "id": "_JBcIKvYx"
    },
    {
      "id": "8GAHvs7Rh-"
    },
    {
      "id": "_hHk3wVdNu"
    },
    {
      "id": "VRo31YkhVW"
    },
    {
      "id": "iyfDEto1I"
    },
    {
      "id": "xNxzAIMAaa"
    },
    {
      "id": "juwEcwtPc"
    },
    {
      "id": "woJ0cgO4Tx"
    },
    {
      "id": "NlBx6Co7vb"
    },
    {
      "id": "oI3il-5O5v"
    },
    {
      "id": "mYNJe4f8p"
    },
    {
      "id": "JotxICkSKg"
    },
    {
      "id": "ZJUrUGJKE6"
    },
    {
      "id": "2hIcj9wpOM"
    },
    {
      "id": "S1vTpLlzO"
    },
    {
      "id": "q2pt2Gw34-"
    },
    {
      "id": "4Gz9duo72Q"
    },
    {
      "id": "m44k_ZJrgl"
    },
    {
      "id": "dYDPiIf2O"
    },
    {
      "id": "qmTva-W7v"
    },
    {
      "id": "VusKAv-SHt"
    },
    {
      "id": "Rr6zoLl7e"
    },
    {
      "id": "9XGhK1I1q"
    },
    {
      "id": "X63Xlbty0"
    },
    {
      "id": "sVyBnbeNp"
    }
  ]
}